DCSync/__init__.py
DCSync/__main__.py
DCSync/core/DCSync.py
DCSync/core/Logger.py
DCSync/core/__init__.py
DCSync/network/Kerberos.py
DCSync/network/LDAP.py
DCSync/network/RPC.py
DCSync/network/__init__.py
DCSync/structures/Credentials.py
DCSync/structures/NTDS.py
DCSync/structures/Target.py
DCSync/structures/__init__.py
DCSync/structures/sAMAccountType.py
DCSync-0.0.1.data/data/requirements.txt
DCSync-0.0.1.dist-info/LICENSE
DCSync-0.0.1.dist-info/METADATA
DCSync-0.0.1.dist-info/WHEEL
DCSync-0.0.1.dist-info/entry_points.txt
DCSync-0.0.1.dist-info/top_level.txt
DCSync-0.0.1.dist-info/RECORD
